eerfile/__init__.py
eerfile/data_models.py
eerfile/read_eer.py
eerfile/render_eer.py
eerfile-0.0.3.dist-info/METADATA
eerfile-0.0.3.dist-info/WHEEL
eerfile-0.0.3.dist-info/licenses/LICENSE
eerfile-0.0.3.dist-info/RECORD
